ariel/__init__.py
ariel/audio_processing.py
ariel/colab_utils.py
ariel/dubbing.py
ariel/speech_to_text.py
ariel/text_to_speech.py
ariel/translation.py
ariel/video_processing.py
ariel/system_settings/diarization.txt
ariel/system_settings/edit_translation.txt
ariel/system_settings/translation.txt
gtech_ariel-0.0.30.dist-info/licenses/LICENSE
gtech_ariel-0.0.30.dist-info/METADATA
gtech_ariel-0.0.30.dist-info/WHEEL
gtech_ariel-0.0.30.dist-info/top_level.txt
gtech_ariel-0.0.30.dist-info/RECORD
