Metadata-Version: 2.4
Name: gtech-ariel
Version: 0.0.30
Summary: Google EMEA gTech Ads Data Science Team's solution to automatically translate and dub video ads into multiple languages using AI.
Home-page: https://github.com/google-marketing-solutions/ariel
Author: Google EMEA gTech Ads Data Science Team
License: Apache Software License 2.0
Keywords: python ai genai speech-to-text translation text-to-speech video dubbing youtube gcp
Classifier: Intended Audience :: Developers
Classifier: Intended Audience :: Science/Research
Classifier: License :: OSI Approved :: Apache Software License
Classifier: Topic :: Scientific/Engineering :: Artificial Intelligence
Requires-Python: >=3.10
License-File: LICENSE
Requires-Dist: absl-py==2.3.0
Requires-Dist: aiohappyeyeballs==2.6.1
Requires-Dist: aiohttp==3.12.13
Requires-Dist: aiosignal==1.3.2
Requires-Dist: alembic==1.16.2
Requires-Dist: annotated-types==0.7.0
Requires-Dist: antlr4-python3-runtime==4.9.3
Requires-Dist: anyio==4.9.0
Requires-Dist: appnope==0.1.4
Requires-Dist: asteroid-filterbanks==0.4.0
Requires-Dist: astunparse==1.6.3
Requires-Dist: attrs==25.3.0
Requires-Dist: av==14.4.0
Requires-Dist: backcall==0.2.0
Requires-Dist: cachetools==5.5.2
Requires-Dist: certifi==2025.6.15
Requires-Dist: cffi==1.17.1
Requires-Dist: charset-normalizer==3.4.2
Requires-Dist: click==8.2.1
Requires-Dist: cloudpickle==3.1.1
Requires-Dist: coloredlogs==15.0.1
Requires-Dist: colorlog==6.9.0
Requires-Dist: contourpy==1.3.2
Requires-Dist: ctranslate2==4.6.0
Requires-Dist: cycler==0.12.1
Requires-Dist: decorator==4.4.2
Requires-Dist: demucs==4.0.1
Requires-Dist: docopt==0.6.2
Requires-Dist: docstring-parser==0.16
Requires-Dist: dora-search==0.1.12
Requires-Dist: einops==0.8.1
Requires-Dist: elevenlabs==2.3.0
Requires-Dist: faster-whisper==1.1.1
Requires-Dist: filelock==3.18.0
Requires-Dist: flatbuffers==25.2.10
Requires-Dist: fonttools==4.58.4
Requires-Dist: frozenlist==1.7.0
Requires-Dist: fsspec==2025.5.1
Requires-Dist: future==1.0.0
Requires-Dist: gast==0.6.0
Requires-Dist: google-api-core==2.25.1
Requires-Dist: google-api-python-client==2.172.0
Requires-Dist: google-auth==2.38.0
Requires-Dist: google-auth-httplib2==0.2.0
Requires-Dist: google-auth-oauthlib==1.2.2
Requires-Dist: google-cloud-aiplatform==1.97.0
Requires-Dist: google-cloud-bigquery==3.34.0
Requires-Dist: google-cloud-core==2.4.3
Requires-Dist: google-cloud-resource-manager==1.14.2
Requires-Dist: google-cloud-storage==2.19.0
Requires-Dist: google-cloud-texttospeech==2.27.0
Requires-Dist: google-crc32c==1.7.1
Requires-Dist: google-genai==1.20.0
Requires-Dist: google-pasta==0.2.0
Requires-Dist: google-resumable-media==2.7.2
Requires-Dist: googleapis-common-protos==1.70.0
Requires-Dist: grpc-google-iam-v1==0.14.2
Requires-Dist: grpcio==1.73.0
Requires-Dist: grpcio-status==1.71.0
Requires-Dist: gspread==6.2.1
Requires-Dist: gspread-dataframe==4.0.0
Requires-Dist: h11==0.16.0
Requires-Dist: h5py==3.14.0
Requires-Dist: hf-xet==1.1.4
Requires-Dist: httpcore==1.0.9
Requires-Dist: httplib2==0.22.0
Requires-Dist: httpx==0.28.1
Requires-Dist: huggingface-hub==0.33.0
Requires-Dist: humanfriendly==10.0
Requires-Dist: hyperpyyaml==1.2.2
Requires-Dist: idna==3.10
Requires-Dist: imageio==2.37.0
Requires-Dist: imageio-ffmpeg==0.6.0
Requires-Dist: ipython==7.34.0
Requires-Dist: jedi==0.19.2
Requires-Dist: jinja2==3.1.6
Requires-Dist: joblib==1.5.1
Requires-Dist: julius==0.2.7
Requires-Dist: keras==3.10.0
Requires-Dist: kiwisolver==1.4.8
Requires-Dist: lameenc==1.8.1
Requires-Dist: libclang==18.1.1
Requires-Dist: lightning==2.5.1.post0
Requires-Dist: lightning-utilities==0.14.3
Requires-Dist: mako==1.3.10
Requires-Dist: markdown==3.8.1
Requires-Dist: markdown-it-py==3.0.0
Requires-Dist: markupsafe==3.0.2
Requires-Dist: matplotlib==3.10.3
Requires-Dist: matplotlib-inline==0.1.7
Requires-Dist: mdurl==0.1.2
Requires-Dist: ml-dtypes==0.4.1
Requires-Dist: moviepy==2.2.1
Requires-Dist: mpmath==1.3.0
Requires-Dist: multidict==6.5.0
Requires-Dist: namex==0.1.0
Requires-Dist: networkx==3.5
Requires-Dist: numpy==2.0.2
Requires-Dist: oauthlib==3.3.0
Requires-Dist: omegaconf==2.3.0
Requires-Dist: onnxruntime==1.22.0
Requires-Dist: openunmix==1.3.0
Requires-Dist: opt-einsum==3.4.0
Requires-Dist: optree==0.16.0
Requires-Dist: optuna==4.4.0
Requires-Dist: packaging==24.2
Requires-Dist: pandas==2.2.3
Requires-Dist: parso==0.8.4
Requires-Dist: pexpect==4.9.0
Requires-Dist: pickleshare==0.7.5
Requires-Dist: pillow==11.2.1
Requires-Dist: primepy==1.3
Requires-Dist: proglog==0.1.12
Requires-Dist: prompt-toolkit==3.0.51
Requires-Dist: propcache==0.3.2
Requires-Dist: proto-plus==1.26.1
Requires-Dist: protobuf==5.29.5
Requires-Dist: ptyprocess==0.7.0
Requires-Dist: pyannote-audio==3.3.2
Requires-Dist: pyannote-core==5.0.0
Requires-Dist: pyannote-database==5.1.3
Requires-Dist: pyannote-metrics==3.2.1
Requires-Dist: pyannote-pipeline==3.0.1
Requires-Dist: pyasn1==0.6.1
Requires-Dist: pyasn1-modules==0.4.2
Requires-Dist: pycparser==2.22
Requires-Dist: pydantic==2.11.7
Requires-Dist: pydantic-core==2.33.2
Requires-Dist: pydub==0.25.1
Requires-Dist: pygments==2.19.1
Requires-Dist: pyloudnorm==0.1.1
Requires-Dist: pyparsing==3.2.3
Requires-Dist: python-dateutil==2.9.0.post0
Requires-Dist: python-dotenv==1.1.0
Requires-Dist: pytorch-lightning==2.5.1.post0
Requires-Dist: pytorch-metric-learning==2.8.1
Requires-Dist: pytz==2025.2
Requires-Dist: pyyaml==6.0.2
Requires-Dist: requests==2.32.4
Requires-Dist: requests-oauthlib==2.0.0
Requires-Dist: retrying==1.3.4
Requires-Dist: rich==13.9.4
Requires-Dist: rsa==4.9.1
Requires-Dist: ruamel-yaml==0.18.14
Requires-Dist: ruamel-yaml-clib==0.2.12
Requires-Dist: scikit-learn==1.6.1
Requires-Dist: scipy==1.15.3
Requires-Dist: semver==3.0.4
Requires-Dist: sentencepiece==0.2.0
Requires-Dist: shapely==2.1.1
Requires-Dist: shellingham==1.5.4
Requires-Dist: six==1.17.0
Requires-Dist: sniffio==1.3.1
Requires-Dist: sortedcontainers==2.4.0
Requires-Dist: soundfile==0.13.1
Requires-Dist: speechbrain==1.0.3
Requires-Dist: sqlalchemy==2.0.41
Requires-Dist: submitit==1.5.3
Requires-Dist: sympy==1.13.1
Requires-Dist: tabulate==0.9.0
Requires-Dist: tensorboard==2.18.0
Requires-Dist: tensorboard-data-server==0.7.2
Requires-Dist: tensorboardx==2.6.4
Requires-Dist: tensorflow==2.18.1
Requires-Dist: tensorflow-io-gcs-filesystem==0.37.1
Requires-Dist: termcolor==3.1.0
Requires-Dist: threadpoolctl==3.6.0
Requires-Dist: tokenizers==0.21.1
Requires-Dist: torch==2.6.0
Requires-Dist: torch-audiomentations==0.12.0
Requires-Dist: torch-pitch-shift==1.2.5
Requires-Dist: torchaudio==2.6.0
Requires-Dist: torchmetrics==1.7.3
Requires-Dist: tqdm==4.67.1
Requires-Dist: traitlets==5.14.3
Requires-Dist: treetable==0.2.5
Requires-Dist: typer==0.16.0
Requires-Dist: typing-extensions==4.14.0
Requires-Dist: typing-inspection==0.4.1
Requires-Dist: tzdata==2025.2
Requires-Dist: uritemplate==4.2.0
Requires-Dist: urllib3==2.5.0
Requires-Dist: wcwidth==0.2.13
Requires-Dist: websockets==15.0.1
Requires-Dist: werkzeug==3.1.3
Requires-Dist: wheel==0.45.1
Requires-Dist: wrapt==1.17.2
Requires-Dist: yarl==1.20.1
Dynamic: author
Dynamic: classifier
Dynamic: description
Dynamic: description-content-type
Dynamic: home-page
Dynamic: keywords
Dynamic: license
Dynamic: license-file
Dynamic: requires-dist
Dynamic: requires-python
Dynamic: summary
